{
  "name": "passthru",
  "title": "jQuery Passthru",
  "description": "Persist query parameters on links throughout your page(s)",
  "keywords": [
    "jquery-plugins",
    "query-passthru",
    "queryPassthru",
    "query",
    "search"
  ],
  "version": "0.1",
  "author": {
    "name": "Kyle Arch",
    "url": "https://github.com/kylearch"
  },
  //"maintainers": [],
  "licenses": [
    {
      "type": "MIT",
      "url": "http://www.opensource.org/licenses/mit-license.php"
    }
  ],
  //"bugs": "https://github.com/jquery-passthru/passthru/issues",
  //"homepage": "http://github.io/jquery-passthru",
  "docs": "https://github.com/jquery-passthru/passthru#readme",
  "dependencies": {
    "jquery": ">=1.4"
  }
}